Metadata-Version: 1.1
Name: pi-shiftreg
Version: 0.1.0
Summary: A simple tool for controlling Shift Registers with RPi GPIO pins
Home-page: https://github.com/kevinpthorne/pi_shiftreg
Author: Kevin Thorne
Author-email: kevinpthorne@gmail.com
License: MIT
Platform: UNKNOWN
Classifier: Development Status :: 4 - Beta
Classifier: Intended Audience :: Science/Research
Classifier: License :: OSI Approved :: MIT License
Classifier: Operating System :: POSIX :: Linux
Classifier: Programming Language :: Python :: 3
Classifier: Programming Language :: Python :: 3.4
Classifier: Programming Language :: Python :: 3.5
